storyboard/__init__.py
storyboard/actions.py
storyboard/images.py
storyboard/osuparse.py
storyboard/sb.py
pystoryboard-0.0.1.dist-info/METADATA
pystoryboard-0.0.1.dist-info/WHEEL
pystoryboard-0.0.1.dist-info/top_level.txt
pystoryboard-0.0.1.dist-info/RECORD
