Metadata-Version: 2.1
Name: pystoryboard
Version: 0.0.1
Summary: Python Package for Storyboarding in osu!
Home-page: UNKNOWN
Author: indexerror
Author-email: lkycst@gmail.com
License: UNKNOWN
Keywords: python,storyboard,osu
Platform: UNKNOWN
Classifier: Development Status :: 3 - Alpha
Classifier: Programming Language :: Python :: 3
Classifier: Operating System :: MacOS :: MacOS X
Classifier: Operating System :: Microsoft :: Windows
